businesslen/__init__.py
businesslen/main.py
businesslen-2.5.0.dist-info/LICENSE
businesslen-2.5.0.dist-info/METADATA
businesslen-2.5.0.dist-info/WHEEL
businesslen-2.5.0.dist-info/top_level.txt
businesslen-2.5.0.dist-info/RECORD
