Metadata-Version: 2.1
Name: businesslen
Version: 2.5.0
Summary: Calculate business days/hours between two datetimes
Home-page: https://github.com/cuong-dang/businesslen
Author: Cuong Dang
Author-email: cuongd@pm.me
License: UNKNOWN
Platform: UNKNOWN
Classifier: Programming Language :: Python :: 3
Classifier: License :: OSI Approved :: MIT License
Classifier: Operating System :: OS Independent
Requires-Dist: holidays
